{
  "supplies": {
    "imbues": false,
    "item6": 0,
    "ammoBp": 0,
    "item2Min": 0,
    "runeBp": 0,
    "item3Min": 0,
    "item1Min": "250",
    "item7Max": 0,
    "item6Max": 0,
    "item2": 0,
    "sortSupplies": false,
    "item6Min": 0,
    "potionBp": 0,
    "SoftBoots": false,
    "item5Max": 0,
    "item1": 238,
    "item5Min": 0,
    "item4Max": 0,
    "item4Min": 0,
    "capValue": 0,
    "item3Max": 0,
    "item2Max": 0,
    "staminaSwitch": false,
    "item5": 0,
    "staminaValue": 900,
    "capSwitch": false,
    "item1Max": "1000",
    "item7": 0,
    "item3": 0,
    "item4": 0
  }
}